mscript/__init__.py
mscript/cli.py
mscript/it.py
mscript/language.def
mscript/mscript_builtins.py
mscript/std/datetime.mscript
mscript/std/ffi.mscript
mscript/std/json.mscript
mscript/std/math.mscript
mscript/std/platform.mscript
mscript/std/random.mscript
mscript/std/re.mscript
mscript/std/string.mscript
mscript/std/sys.mscript
mscript/std/time.mscript
mscript_lang-0.68.dist-info/METADATA
mscript_lang-0.68.dist-info/WHEEL
mscript_lang-0.68.dist-info/entry_points.txt
mscript_lang-0.68.dist-info/top_level.txt
mscript_lang-0.68.dist-info/RECORD
