Metadata-Version: 2.4
Name: mscript-lang
Version: 0.68
Summary: Mscript: A lightweight interpreted scripting language
Author: Momo-AUX1
Classifier: Programming Language :: Python :: 3
Classifier: License :: OSI Approved :: MIT License
Classifier: Operating System :: OS Independent
Requires-Python: >=3.7
Requires-Dist: lark
Dynamic: author
Dynamic: classifier
Dynamic: description-content-type
Dynamic: requires-dist
Dynamic: requires-python
Dynamic: summary
